README
setup.py
editor/__init__.py
editor/color_selector.py
editor/editor.py
editor/image_region_placer.py
editor/proxy_dialog.py
editor/resizable.py
editor/state_manager.py
kytten/__init__.py
kytten/button.py
kytten/checkbox.py
kytten/dialog.py
kytten/document.py
kytten/file_dialogs.py
kytten/frame.py
kytten/layout.py
kytten/menu.py
kytten/override.py
kytten/safe_eval.py
kytten/scrollable.py
kytten/scrollbar.py
kytten/slider.py
kytten/text_input.py
kytten/theme.py
kytten/widgets.py
kytten.egg-info/PKG-INFO
kytten.egg-info/SOURCES.txt
kytten.egg-info/dependency_links.txt
kytten.egg-info/not-zip-safe
kytten.egg-info/requires.txt
kytten.egg-info/top_level.txt