Metadata-Version: 1.0
Name: kytten
Version: 6.0.0
Summary: GUI Framework for Pyglet
Home-page: https://github.com/kitanata/kytten
Author: Conrad 'Lynx' Wong(originator) Raymond Chandler III(fork)
Author-email: UNKNOWN
License: BSD
Download-URL: https://github.com/kitanata/kytten/tarball/master
Platform: UNKNOWN
Classifier: Development Status :: 5 - Production/Stable
Classifier: Environment :: MacOS X
Classifier: Environment :: Win32 (MS Windows)
Classifier: Environment :: X11 Applications
Classifier: Intended Audience :: Developers
Classifier: License :: OSI Approved :: BSD License
Classifier: Natural Language :: English
Classifier: Operating System :: MacOS :: MacOS X
Classifier: Operating System :: Microsoft :: Windows
Classifier: Operating System :: POSIX :: Linux
Classifier: Programming Language :: Python
Classifier: Topic :: Software Development :: Libraries :: Python Modules
Classifier: Topic :: Games/Entertainment
